examiner/__init__.py
examiner/examiner_app.py
examiner/config/__init__.py
examiner/config/config.py
examiner/databases/__init__.py
examiner/databases/sqlite_db.py
examiner/notification/__init__.py
examiner/notification/base_notification.py
examiner/notification/mac_notification.py
examiner/notification/notification_factory.py
examiner/utils/__init__.py
examiner/utils/log.py
examiner/utils/tools.py
examiner-0.0.1.dist-info/METADATA
examiner-0.0.1.dist-info/WHEEL
examiner-0.0.1.dist-info/top_level.txt
examiner-0.0.1.dist-info/RECORD
